<?xml version="1.0" encoding="UTF-8" standalone="yes"?>
<root>
  <title>СК Белоруссии сообщил о проверке информации про изнасилования в изоляторах</title>
  <second_title/>
  <description>Следственный комитет Белоруссии «проверяет информацию из интернет-ресурсов об изнасиловании женщин в местах временного содержания», сообщается в телеграм-канале ведомства.</description>
  <keywords>новости, политика, расследование, репортаж, интервью, реакция, исследование, опрос, тест, президент, приговор, доллар, нефть, экономика, цены, средства, информация, компания, фото, видео, украина, сепаратисты, война, краткий пересказ, бестселлер</keywords>
  <nameTag>новости</nameTag>
  <name>Следственный комитет Белоруссии</name>
  <url>https://t.me/skgovby/2962</url>
  <date>20.8.2020</date>
  <content>&lt;p&gt;Следственный комитет Белоруссии «проверяет информацию из интернет-ресурсов об изнасиловании женщин в местах временного содержания», сообщается в телеграм-канале ведомства.&lt;/p&gt;&lt;p&gt;В СК отметили, что на 20 августа зарегистрированных сообщений или заявлений об изнасилованиях в следственных подразделениях нет. Также нет такой информации «от граждан, опрошенных в связи с событиями 9-12 августа».&lt;/p&gt;&lt;p&gt;Кроме того, как утверждают в СК, «ни в одном из предоставленных медицинскими учреждениями документов такая информация также не содержится».&lt;/p&gt;</content>
</root>