<?xml version="1.0" encoding="UTF-8" standalone="yes"?>
<root>
  <title>ФБК: в омской больнице говорят о «нетранспортабельном состоянии» Навального</title>
  <second_title/>
  <description>Врачи омской больницы, куда госпитализирован Алексей Навальный, отказывают в его транспортировке в другую клинику, утверждая, что он находится в нетранспортабельном состоянии. Об этом в твиттере сообщил юрист ФБК Иван Жданов.</description>
  <keywords>новости, политика, расследование, репортаж, интервью, реакция, исследование, опрос, тест, президент, приговор, доллар, нефть, экономика, цены, средства, информация, компания, фото, видео, украина, сепаратисты, война, краткий пересказ, бестселлер</keywords>
  <nameTag>новости</nameTag>
  <name>Иван Жданов</name>
  <url>https://twitter.com/IoannZH/status/1296442021515796485</url>
  <date>20.8.2020</date>
  <content>&lt;p&gt;Врачи омской больницы, куда госпитализирован Алексей Навальный, отказывают в его транспортировке в другую клинику, утверждая, что он находится в нетранспортабельном состоянии. Об этом в твиттере сообщил юрист ФБК Иван Жданов.&lt;/p&gt;</content>
</root>