<?xml version="1.0" encoding="UTF-8" standalone="yes"?>
<root>
  <title>ยซะัััะตะฝะธั ะฟะพัะปะต ัะบะพะปะฐยโ ััะพ ัััะตะบั ะฒะฐะบัะธะฝั ะธะปะธ ะผะพะตะน ะฟะพะดะฒะธะถะฝะพะน ะฟัะธัะธะบะธ?ยป ะกะฟะตัะบะพั ะกะฒะตัะปะฐะฝะฐ ะะตะนัะตัยโ ะพยัะพะผ, ะบะฐะบ ะพะฝะฐ ะธัะฟัััะฒะฐะตั ะฝะฐยัะตะฑะต ะฒะฐะบัะธะฝั ะพัยะบะพัะพะฝะฐะฒะธัััะฐ</title>
  <second_title/>
  <description>ะกะฟะตัะธะฐะปัะฝัะน ะบะพััะตัะฟะพะฝะดะตะฝั ยซะะตะดัะทัยป ะกะฒะตัะปะฐะฝะฐ ะะตะนัะตั ะฒยะฟะพะดะบะฐััะต ยซะขะตะบัั ะฝะตะดะตะปะธยป ัะฐััะบะฐะทัะฒะฐะตั ะพยัะพะผ, ะบะฐะบ ะพะฝะฐ ััะฐะปะฐ ะดะพะฑัะพะฒะพะปััะตะผ ะฒยะธััะปะตะดะพะฒะฐะฝะธั ัะพััะธะนัะบะพะน ะฒะฐะบัะธะฝั ะพัยะบะพัะพะฝะฐะฒะธัััะฐ.</description>
  <keywords>meduza, ะฝะพะฒะพััะธ, ะผะตะดัะทะฐ, ะฟะพะปะธัะธะบะฐ, ะผะตะดะธัะธะฝะฐ, ะบะพะฒะธะด, ะบะพัะพะฝะฐะฒะธััั, ะกะฒะตัะปะฐะฝะฐ ะะตะนัะตั, ะฒะฐะบัะธะฝะฐ, ะธัะฟััะฐะฝะธะต, ัะตัั, ะฟะพะดะบะฐัั, ัะตะบัั ะฝะตะดะตะปะธ, ะฟะพะปะธะบะปะธะฝะธะบะฐ, ะฒะธััั</keywords>
  <nameTag>ะฟะพะดะบะฐััั</nameTag>
  <name>ะะตั ะธััะพัะฝะธะบะฐ</name>
  <url>ะะตั ัััะปะบะธ ะฝะฐ ะธััะพัะฝะธะบ</url>
  <date>4.10.2020</date>
  <content>&lt;p&gt;ะกะฟะตัะธะฐะปัะฝัะน ะบะพััะตัะฟะพะฝะดะตะฝั ยซะะตะดัะทัยป ะกะฒะตัะปะฐะฝะฐ ะะตะนัะตั ะฒยะฟะพะดะบะฐััะต ยซะขะตะบัั ะฝะตะดะตะปะธยป ัะฐััะบะฐะทัะฒะฐะตั ะพยัะพะผ, ะบะฐะบ ะพะฝะฐ &lt;a href="https://meduza.io/feature/2020/09/29/spetskor-meduzy-svetlana-reyter-stala-dobrovoltsem-na-ispytaniyah-vaktsiny-ot-koronavirusa-sputnik-v-my-poprosili-ee-zapisyvat-svoi-oschuscheniya-den-za-dnem" target="_blank" rel="noopener"&gt;ััะฐะปะฐ ะดะพะฑัะพะฒะพะปััะตะผ&lt;/a&gt; ะฒยะธััะปะตะดะพะฒะฐะฝะธั ัะพััะธะนัะบะพะน ะฒะฐะบัะธะฝั ะพัยะบะพัะพะฝะฐะฒะธัััะฐ.&lt;/p&gt;&lt;p&gt;ะยัะตะณะธัััะฐัะธะธ ะฟะตัะฒะพะน ะฒยะผะธัะต ะฒะฐะบัะธะฝั ะพัยะบะพัะพะฝะฐะฒะธัััะฐ ะะพััะธั ะพะฑััะฒะธะปะฐ 11ยะฐะฒะณัััะฐ. ะยัะพะผั ะผะพะผะตะฝัั ะฑัะปะธ ะฟัะพะฒะตะดะตะฝั ะธัะฟััะฐะฝะธั ะฝะฐยะฝะตะฑะพะปััะพะน ะณััะฟะฟะต ะดะพะฑัะพะฒะพะปััะตะฒ (ะพะดะธะฝ ะธะทยะฝะธั ัะฐััะบะฐะทัะฒะฐะป ะฝะฐะผ ะพะฑยััะพะผ ะฒยะฟะพะดะบะฐััะต &lt;a href="https://meduza.io/episodes/2020/08/19/rossiyskaya-vaktsina-kotoruyu-putin-nazval-pervym-v-mire-zaregistrirovannym-lekarstvom-ot-koronavirusa-pochemu-eto-skoree-propaganda-chem-proryv" target="_blank" rel="noopener"&gt;ยซะงัะพ ัะปััะธะปะพััยป&lt;/a&gt;). ะยัะตะนัะฐั ัะพะทะดะฐัะตะปะธ ะฒะฐะบัะธะฝัยโ ะะฐัะธะพะฝะฐะปัะฝัะน ะธััะปะตะดะพะฒะฐัะตะปััะบะธะน ัะตะฝัั ัะฟะธะดะตะผะธะพะปะพะณะธะธ ะธยะผะธะบัะพะฑะธะพะปะพะณะธะธ ะธะผะตะฝะธ ะะฐะผะฐะปะตะธยโ ะดะพะปะถะฝั ะฟัะพะฒะตััะธ ัะธัะพะบะพะผะฐัััะฐะฑะฝัะต ะบะปะธะฝะธัะตัะบะธะต ะธััะปะตะดะพะฒะฐะฝะธั ััะตััะตะน ัะฐะทั. ะะปั ััะพะณะพ ะฝัะถะฝั ะดะตัััะบะธ ััััั ะดะพะฑัะพะฒะพะปััะตะฒ.&lt;/p&gt;&lt;p&gt;ะกะฒะตัะปะฐะฝะฐ ะะตะนัะตั ะพะฑัััะฝัะตั, ะทะฐัะตะผ ะพะฝะฐ ะฟะพะดะฐะปะฐ ะทะฐัะฒะบั, ะบะฐะบ ะฒัะณะปัะดัั ะธัะฟััะฐะฝะธั, ะบัะพ ะฒยะฝะธั ััะฐััะฒัะตั (ะฒัะตะณะดะฐยะปะธ ััะพ ะดะพะฑัะพะฒะพะปัะฝะพะต ัะตัะตะฝะธะต ะธะปะธ ัะฐะฑะพัะพะดะฐัะตะปะธ ะทะฐััะฐะฒะปััั ัะพัััะดะฝะธะบะพะฒ) ะธยะผะพะถะฝะพยะปะธ ะฟะพะฝััั, ััะพ ัะตะฑะต ะดะฐะปะธยโ ะดะตะนััะฒััััั ะฒะฐะบัะธะฝั ะธะปะธ ะฟะปะฐัะตะฑะพ.&lt;/p&gt;&lt;p&gt;๐ ะะพะดะฟะธััะฒะฐะนัะตัั ะฝะฐยะฟะพะดะบะฐัั ยซะขะตะบัั ะฝะตะดะตะปะธยป, ะผัยะตััั ะฝะฐยะฒัะตัย&lt;a href="https://we.fo/1286397272" target="_blank" rel="noopener"&gt;ะพัะฝะพะฒะฝัั ะฟะปะฐััะพัะผะฐั&lt;/a&gt;.&lt;/p&gt;</content>
</root>