<?xml version="1.0" encoding="UTF-8" standalone="yes"?>
<root>
  <title>Норвежский террорист Андерс Брейвик подал прошение о досрочном освобождении</title>
  <second_title/>
  <description>Норвежец Андерс Брейвик, приговоренный к 21 году заключения за убийство 77 человек в 2011 году, подал прошение об условно-досрочном освобождении. Об этом норвежскому таблоиду Verdens Gang сообщил его адвокат Ойстен Стуррвик.</description>
  <keywords>новости, политика, расследование, репортаж, интервью, реакция, исследование, опрос, тест, президент, приговор, доллар, нефть, экономика, цены, средства, информация, компания, фото, видео, украина, сепаратисты, война, краткий пересказ, бестселлер</keywords>
  <nameTag>новости</nameTag>
  <name>Verdens Gang</name>
  <url>https://www.vg.no/nyheter/innenriks/i/weEvVP/breivik-begjaerer-seg-loeslatt-fra-fengsel</url>
  <date>16.9.2020</date>
  <content>&lt;p&gt;Норвежец Андерс Брейвик, приговоренный к 21 году заключения за убийство 77 человек в 2011 году, подал прошение об условно-досрочном освобождении. Об этом норвежскому таблоиду Verdens Gang сообщил его адвокат Ойстен Стуррвик.&lt;/p&gt;&lt;p&gt;Прошение подписано двумя именами: Андерс Беринг Брейвик и Фьотольф Хансен (второе имя осужденный &lt;a href="https://meduza.io/news/2017/06/09/anders-breyvik-smenil-imya-i-familiyu" target="_blank" rel="noopener"&gt;взял&lt;/a&gt; в 2017 году).&lt;/p&gt;&lt;p&gt;По словам адвоката, право просить о досрочном освобождении в случае с Брейвиком появляется после 10 лет заключения. При этом террорист отсидел меньший срок — его арестовали в июле 2011-го, а приговор ему вынесли в августе 2012-го. «Он хочет этого сейчас. Он провел в одиночной камере более восьми лет после завершения суда», — сказал адвокат.&lt;/p&gt;&lt;p&gt;Также Брейвик намерен начать новый судебный процесс против государства, считая, что его права ущемляют. В 2015 году он уже судился с государством, жалуясь на нарушение своих прав в тюрьме. Брейвик говорил, что условия его содержания бесчеловечны и унижают достоинство. Тогда его частично поддержал суд в Осло, но апелляционный суд встал на сторону норвежских властей. ЕСПЧ отклонил жалобу Брейвика на «бесчеловечное обращение» в тюрьме.&lt;/p&gt;</content>
</root>