<?xml version="1.0" encoding="UTF-8" standalone="yes"?>
<root>
  <title>Мадонна снимет фильм о себе</title>
  <second_title/>
  <description>Американская певица Мадонна станет режиссером и сценаристом фильма-автобиографии.</description>
  <keywords>новости, политика, расследование, репортаж, интервью, реакция, исследование, опрос, тест, президент, приговор, доллар, нефть, экономика, цены, средства, информация, компания, фото, видео, украина, сепаратисты, война, краткий пересказ, бестселлер</keywords>
  <nameTag>новости</nameTag>
  <name>madonna.com</name>
  <url>https://www.madonna.com/news/title/universal-pictures-announces-film-based-on-the-untold-true-story-of-madonna</url>
  <date>16.9.2020</date>
  <content>&lt;p&gt;Американская певица Мадонна станет режиссером и сценаристом фильма-автобиографии.&lt;/p&gt;&lt;p&gt;Производством картины, посвященной карьере поп-звезды, займется компания Universal Pictures. Название и сроки выхода ленты пока не разглашаются.&lt;/p&gt;&lt;p&gt;Соавтором сценария выступит американская писательница Брук Бьюзи-Морио, известная под псевдонимом Диабло Коуди. В 2008 году она была удостоена «Оскара» за лучший оригинальный сценарий к фильму «Джуно».&lt;/p&gt;&lt;p&gt;«Я хочу рассказать о том, каким потрясающим путешествием стала для меня жизнь артиста, музыканта, танцора и человека, который пытается идти в этом мире своей собственной дорогой, — говорится в заявлении Мадонны на ее официальном сайте. — В центре внимания этого фильма всегда будет музыка. Музыка поддерживала меня, а искусство сохраняло жизнь. Есть еще так много нерассказанных и вдохновляющих историй — и кто их лучше всего расскажет, как не я сама».&lt;/p&gt;</content>
</root>