<?xml version="1.0" encoding="UTF-8" standalone="yes"?>
<root>
  <title>Что изменит пенсионная реформа лично для меня? Вот справка для каждой категории будущих пенсионеров</title>
  <second_title/>
  <description>Госдума одобрила в третьем чтении законопроект о повышении пенсионного возраста. «Медуза» составила краткие справки о том, что изменится для каждой категории будущих пенсионеров после того, как закончится переходный период. </description>
  <keywords>новости, политика, расследование, репортаж, интервью, реакция, исследование, опрос, тест, президент, приговор, доллар, нефть, экономика, цены, средства, информация, компания, фото, видео, украина, сепаратисты, война, краткий пересказ, бестселлер</keywords>
  <nameTag>разбор</nameTag>
  <name>Meduza</name>
  <url/>
  <date>27.9.2018</date>
  <content>&lt;p&gt;Госдума &lt;a href="https://meduza.io/news/2018/09/27/gosduma-okonchatelno-odobrila-pensionnuyu-reformu" target="_blank" rel="noopener"&gt;одобрила&lt;/a&gt; в третьем чтении законопроект о повышении пенсионного возраста. «Медуза» составила краткие справки о том, что изменится для каждой категории будущих пенсионеров после того, как закончится переходный период. &lt;/p&gt;</content>
</root>