<?xml version="1.0" encoding="UTF-8" standalone="yes"?>
<root>
  <title>Новыми ведущими «Орла и решки» стали Александр Гудков и Иван Дорн</title>
  <second_title/>
  <description>Новыми ведущими программы о путешествиях «Орел и решка» стали шоумен Александр Гудков и певец Иван Дорн. Об этом сообщил телеканал «Пятница!», на котором выходит программа.</description>
  <keywords>новости, политика, расследование, репортаж, интервью, реакция, исследование, опрос, тест, президент, приговор, доллар, нефть, экономика, цены, средства, информация, компания, фото, видео, украина, сепаратисты, война, краткий пересказ, бестселлер</keywords>
  <nameTag>новости</nameTag>
  <name>Пятница!</name>
  <url>https://www.instagram.com/p/CKggGgoBzTJ/</url>
  <date>26.1.2021</date>
  <content>&lt;p&gt;Новыми ведущими программы о путешествиях «Орел и решка» стали шоумен Александр Гудков и певец Иван Дорн. Об этом сообщил телеканал «Пятница!», на котором выходит программа.&lt;/p&gt;&lt;p&gt;Новый сезон «Орла и решки» начнется 15 февраля. Он станет уже десятым по счету. Впервые за годы существования программы ее ведущими будут двое мужчин, &lt;a href="https://daily.afisha.ru/news/46565-aleksandr-gudkov-i-ivan-dorn-stali-novymi-veduschimi-shou-orel-i-reshka/" target="_blank" rel="noopener"&gt;отмечает&lt;/a&gt; «Афиша».&lt;/p&gt;</content>
</root>