<?xml version="1.0" encoding="UTF-8" standalone="yes"?>
<root>
  <title>И.о. президента Киргизии подал в отставку через полдня после отставки президента. Новым главой государства станет премьер — еще 10 дней назад он сидел в тюрьме</title>
  <second_title/>
  <description>Спикер парламента Киргизии Канатбек Исаев подал в отставку. Об этом сообщает 24.kg.</description>
  <keywords>новости, политика, расследование, репортаж, интервью, реакция, исследование, опрос, тест, президент, приговор, доллар, нефть, экономика, цены, средства, информация, компания, фото, видео, украина, сепаратисты, война, краткий пересказ, бестселлер</keywords>
  <nameTag>новости</nameTag>
  <name>24.kg</name>
  <url>https://24.kg/vlast/169490_spiker_kanat_isaev_otkazalsya_otpolnomochiyio_prezidenta/</url>
  <date>15.10.2020</date>
  <content>&lt;p&gt;Спикер парламента Киргизии Канатбек Исаев подал в отставку. Об этом сообщает 24.kg.&lt;/p&gt;&lt;p&gt;С утра 15 октября Исаев как спикер парламента был исполняющим обязанности президента Киргизии — он автоматически получил эту должность после того, как об отставке объявил президент Сооронбай Жээнбеков.&lt;/p&gt;&lt;p&gt;Теперь исполнение обязанностей главы государства перейдет к действующему премьер-министру страны Садыру Жапарову. Его кандидатуру на этой должности еще должен будет утвердить парламент.&lt;/p&gt;</content>
</root>