<?xml version="1.0" encoding="UTF-8" standalone="yes"?>
<root>
  <title>«Всем привет из Кремлевского централа». Навальный написал обращение из СИЗО «Матросская тишина»</title>
  <second_title/>
  <description>Оппозиционер Алексей Навальный написал обращение из следственного изолятора «Матросская тишина», в котором он находится с 18 января. Обращение политика опубликовали в его инстаграме.</description>
  <keywords>новости, политика, расследование, репортаж, интервью, реакция, исследование, опрос, тест, президент, приговор, доллар, нефть, экономика, цены, средства, информация, компания, фото, видео, украина, сепаратисты, война, краткий пересказ, бестселлер</keywords>
  <nameTag>новости</nameTag>
  <name>Алексей Навальный</name>
  <url>https://www.instagram.com/p/CKOx19NlDzw/</url>
  <date>19.1.2021</date>
  <content>&lt;p&gt;Оппозиционер Алексей Навальный написал обращение из следственного изолятора «Матросская тишина», в котором он находится с 18 января. Обращение политика опубликовали в его инстаграме.&lt;/p&gt;&lt;p&gt;В обращении Навальный рассказал об условиях в СИЗО, которые напомнили ему о клинике «Шарите» в Берлине, где он находился после отравления, предположительно, ядом из группы «Новичок».&lt;/p&gt;&lt;p&gt;Политик заявил, что не жалеет о том, что вернулся из Германии в Россию, и назвал свое решение рациональным.&lt;/p&gt;</content>
</root>