<?xml version="1.0" encoding="UTF-8" standalone="yes"?>
<root>
  <title>Майкла Калви освободили из-под домашнего ареста</title>
  <second_title/>
  <description>Верховный суд (ВС) РФ освободил основателя фонда Baring Vostok Майкла Калви из-под домашнего ареста, сообщает РИА Новости.</description>
  <keywords>новости, политика, расследование, репортаж, интервью, реакция, исследование, опрос, тест, президент, приговор, доллар, нефть, экономика, цены, средства, информация, компания, фото, видео, украина, сепаратисты, война, краткий пересказ, бестселлер</keywords>
  <nameTag>новости</nameTag>
  <name>РИА Новости</name>
  <url>https://t.me/rian_ru/64940</url>
  <date>12.11.2020</date>
  <content>&lt;p&gt;Верховный суд (ВС) РФ освободил основателя фонда Baring Vostok Майкла Калви из-под домашнего ареста, сообщает РИА Новости.&lt;/p&gt;&lt;p&gt;Как уточняет «Интерфакс», Калви и другим фигурантам дела Baring Vostok назначили меру пресечения в виде запрета определенных действий.&lt;/p&gt;&lt;p&gt;В частности, им запретили находиться в помещении банка «Восточный» и Первого коллекторского бюро (ПКБ, компания Калви). Калви также запретили выходить из дома ночью и обязали своевременно приходить в суд.&lt;/p&gt;&lt;p&gt;«Я очень рад, что освобожден, — сказал бизнесмен после суда. —Я собираюсь в ближайшее время выйти на работу [в Baring Vostok] » (цитата по «Интерфаксу»).&lt;/p&gt;&lt;p&gt;ВС 12 ноября рассматривал ходатайство прокуратуры о продлении &lt;a href="https://meduza.io/news/2020/02/12/sud-perevel-treh-figurantov-dela-baring-vostok-iz-sizo-pod-domashniy-arest-oni-proveli-pod-strazhey-god" target="_blank" rel="noopener"&gt;домашнего ареста&lt;/a&gt; Калви и другим обвиняемым.&lt;/p&gt;</content>
</root>