<?xml version="1.0" encoding="UTF-8" standalone="yes"?>
<root>
  <title>Суд назвал иск журналистов к администрации Кремля нарушением конституционного строя</title>
  <second_title/>
  <description>Тверской суд Москвы отказался принять иск сетевого издания Sota Vision к администрации президента РФ, посчитав его «нарушением основ конституционного строя».</description>
  <keywords>новости, политика, расследование, репортаж, интервью, реакция, исследование, опрос, тест, президент, приговор, доллар, нефть, экономика, цены, средства, информация, компания, фото, видео, украина, сепаратисты, война, краткий пересказ, бестселлер</keywords>
  <nameTag>новости</nameTag>
  <name>Sota Vision</name>
  <url>https://t.me/sotavision/15949</url>
  <date>11.2.2021</date>
  <content>&lt;p&gt;Тверской суд Москвы &lt;a href="https://mos-gorsud.ru/rs/tverskoj/services/cases/claim-admin/details/77903e40-5fa0-11eb-aaa7-eb628e237248" target="_blank" rel="noopener"&gt;отказался принять&lt;/a&gt; иск сетевого издания Sota Vision к администрации президента РФ, посчитав его «нарушением основ конституционного строя».&lt;/p&gt;&lt;p&gt;Цитата из определения судьи Екатерины Коротовой опубликована в телеграм-канале Sota Vision.&lt;/p&gt;&lt;p&gt;В декабре 2020 года Sota Vision подавало иск к администрации Кремля из-за отказа в аккредитации на пресс-конференцию Владимира Путина, что журналисты посчитали нарушением закона «О СМИ». «Закон не предполагает возможности отказа в аккредитации, если соблюдены правила подачи заявки. Соблюдены они были. Нежелание государственного органа видеть того или иного журналиста не может являться причиной отказа», — &lt;a href="https://t.me/sotavision/12020" target="_blank" rel="noopener"&gt;поясняли&lt;/a&gt; в Sota Vision.&lt;/p&gt;&lt;p&gt;Журналисты намерены обжаловать решение Тверского суда Москвы.&lt;/p&gt;</content>
</root>