<?xml version="1.0" encoding="UTF-8" standalone="yes"?>
<root>
  <title>Верховный суд России ликвидировал партию «Народ против коррупции». Ее возглавлял двоюродный племянник Путина</title>
  <second_title/>
  <description>Верховный суд России ликвидировал политическую партию «Народ против коррупции», которую возглавлял двоюродный племянник президента Роман Путин. </description>
  <keywords>новости, политика, расследование, репортаж, интервью, реакция, исследование, опрос, тест, президент, приговор, доллар, нефть, экономика, цены, средства, информация, компания, фото, видео, украина, сепаратисты, война, краткий пересказ, бестселлер</keywords>
  <nameTag>новости</nameTag>
  <name>МБХ медиа</name>
  <url>https://mbk-news.appspot.com/news/party-putin/</url>
  <date>16.11.2020</date>
  <content>&lt;p&gt;Верховный суд России ликвидировал политическую партию «Народ против коррупции», которую возглавлял двоюродный племянник президента Роман Путин. &lt;/p&gt;&lt;p&gt;Партия была ликвидирована по иску Минюста. Ведомство официально причины иска, поданного в конце сентября, не комментировало.&lt;/p&gt;&lt;p&gt;Ранее ЦИК называл «Народ против коррупции» в числе четырех партий, которые могут быть ликвидированы из-за того, что семь лет подряд не участвовали в выборах.&lt;/p&gt;</content>
</root>