<?xml version="1.0" encoding="UTF-8" standalone="yes"?>
<root>
  <title>В России запустят электрокардиограмму и уведомление об аритмии на Apple Watch</title>
  <second_title/>
  <description>В России пользователи Apple Watch смогут воспользоваться функциями снятия электрокардиограммы и отслеживания аритмии.</description>
  <keywords>новости, политика, расследование, репортаж, интервью, реакция, исследование, опрос, тест, президент, приговор, доллар, нефть, экономика, цены, средства, информация, компания, фото, видео, украина, сепаратисты, война, краткий пересказ, бестселлер</keywords>
  <nameTag>новости</nameTag>
  <name>Meduza</name>
  <url/>
  <date>2.11.2020</date>
  <content>&lt;p&gt;В России пользователи Apple Watch смогут воспользоваться функциями снятия электрокардиограммы и отслеживания аритмии.&lt;/p&gt;&lt;p&gt;Приложение «ЭКГ» для Apple Watch Series 4 и старше станет доступно с выходом следующего обновления программного обеспечения вместе с iOS 14.2 и watchOS 7.1, говорится в сообщении Apple, поступившем в «Медузу».&lt;/p&gt;&lt;p&gt;«ЭКГ» позволяет снимать электрокардиограмму прямо с запястья, а при таких симптомах, как учащенное или нерегулярное сердцебиение, записывает сердечный ритм и помогает сообщить об этом врачу.&lt;/p&gt;&lt;p&gt;Функция уведомления о нерегулярном сердечном ритме будет доступна на Apple Watch начиная уже с Series 3. Она периодически проверяет ритм сердца в фоновом режиме и присылает уведомление в случае обнаружения нерегулярного ритма, вызванного, предположительно, мерцательной аритмией.&lt;/p&gt;&lt;p&gt;Приложение «ЭКГ» и функция уведомления о нерегулярном сердечном ритме, в соответствии с сертификацией Росздравнадзора, не являются медицинскими устройствами и не предназначены для использования при врачебных обследованиях и самостоятельной постановки диагноза.&lt;/p&gt;</content>
</root>