<?xml version="1.0" encoding="UTF-8" standalone="yes"?>
<root>
  <title>Власти Махачкалы сорвали рекламные плакаты с магазина New Balance после того, как глава Дагестана потребовал навести порядок с рекламой в городе</title>
  <second_title/>
  <description>С магазина New Balance в Махачкале сорвали рекламные плакаты, повредив световые короба. Об этом сообщается в инстаграм-аккаунте магазина.</description>
  <keywords>новости, политика, расследование, репортаж, интервью, реакция, исследование, опрос, тест, президент, приговор, доллар, нефть, экономика, цены, средства, информация, компания, фото, видео, украина, сепаратисты, война, краткий пересказ, бестселлер</keywords>
  <nameTag>новости</nameTag>
  <name>New Balance</name>
  <url>https://www.instagram.com/p/CG0I00GhEu6/</url>
  <date>27.10.2020</date>
  <content>&lt;p&gt;С магазина New Balance в Махачкале сорвали рекламные плакаты, повредив световые короба. Об этом сообщается в инстаграм-аккаунте магазина.&lt;/p&gt;&lt;p&gt;«Ночью какие-то вандалы повредили наши короба, сорвали нашу рекламу, вывеску. Просто поступили, мягко говоря, не по-человечески», — рассказал автор видео в инстаграме магазина.&lt;/p&gt;&lt;p&gt;В подписи к ролику говорится, что «снималась реклама по указанию администрации» (вероятно, речь идет об администрации Махачкалы). Магазин о снятии рекламы не предупредили, ущерб за повреждение световых коробов никто не возместил.&lt;/p&gt;&lt;p&gt;23 октября временно исполняющий обязанности главы Дагестана Сергей Меликов &lt;a href="https://rgvktv.ru/politika/68856" target="_blank" rel="noopener"&gt;потребовал&lt;/a&gt; от администрации Махачкалы навести порядок с наружной рекламой — например, частично заменить коммерческую рекламу на портреты врачей, которые умерли во время пандемии. 27 октября власти Махачкалы &lt;a href="https://www.mkala.ru/info/news/2020/10/27/news_24983.html" target="_blank" rel="noopener"&gt;провели&lt;/a&gt; совещание с предпринимателями по поводу рекламы в городе.&lt;/p&gt;</content>
</root>