<?xml version="1.0" encoding="UTF-8" standalone="yes"?>
<root>
  <title>В России вступил в силу закон, обязывающий соцсети искать и блокировать информацию о несогласованных митингах</title>
  <second_title/>
  <description>1 февраля в России вступили в силу поправки к закону «Об информации…», которые обязывают социальные сети с ежедневной аудиторией 500 тысяч пользователей из России мониторить и блокировать противоправную информацию.</description>
  <keywords>новости, политика, расследование, репортаж, интервью, реакция, исследование, опрос, тест, президент, приговор, доллар, нефть, экономика, цены, средства, информация, компания, фото, видео, украина, сепаратисты, война, краткий пересказ, бестселлер</keywords>
  <nameTag>новости</nameTag>
  <name>Официальный интернет-портал правовой информации</name>
  <url>http://publication.pravo.gov.ru/Document/View/0001202012300062</url>
  <date>1.2.2021</date>
  <content>&lt;p&gt;1 февраля в России вступили в силу &lt;a href="http://publication.pravo.gov.ru/Document/View/0001202012300062" target="_blank" rel="noopener"&gt;поправки&lt;/a&gt; к закону «Об информации…», которые обязывают социальные сети с ежедневной аудиторией 500 тысяч пользователей из России мониторить и блокировать противоправную информацию.&lt;/p&gt;&lt;p&gt;Соцсети должны добровольно блокировать:&lt;/p&gt;&lt;p&gt;Помимо этого соцсети обязали «не допускать», чтобы на их страницах размещали сведения, составляющие государственную тайну, призывы к терроризму или оправдание террористической деятельности, экстремистские материалы, а также пропаганду порнографии, культа насилия и жестокости, материалы с нецензурной бранью и дискриминационную информацию.&lt;/p&gt;&lt;p&gt;Закон не предусматривает никакого наказания для тех, кто откажется это делать. Авторы закона &lt;a href="https://tass.ru/ekonomika/10323149" target="_blank" rel="noopener"&gt;рассчитывали&lt;/a&gt;, что соцсети станут добровольно выполнять эти требования. Один из авторов документа, депутат-единоросс Сергей Боярский отмечал, что инициатива не направлена на полный запрет нецензурной лексики в соцсетях.&lt;/p&gt;</content>
</root>