<?xml version="1.0" encoding="UTF-8" standalone="yes"?>
<root>
  <title>«Коммерсант»: медикам продлят выплаты за работу с COVID-19 на 2021 год</title>
  <second_title/>
  <description>Правительство России продлит на 2021 год доплаты медикам за работу с заболевшими COVID-19, пишет «Коммерсант».</description>
  <keywords>новости, политика, расследование, репортаж, интервью, реакция, исследование, опрос, тест, президент, приговор, доллар, нефть, экономика, цены, средства, информация, компания, фото, видео, украина, сепаратисты, война, краткий пересказ, бестселлер</keywords>
  <nameTag>новости</nameTag>
  <name>Коммерсант</name>
  <url>https://www.kommersant.ru/doc/4541320</url>
  <date>23.10.2020</date>
  <content>&lt;p&gt;Правительство России продлит на 2021 год доплаты медикам за работу с заболевшими COVID-19, пишет «Коммерсант».&lt;/p&gt;&lt;p&gt;Накануне на встрече с фракцией «Единой России» министр финансов Антон Силуанов &lt;a href="https://tass.ru/ekonomika/9784677" target="_blank" rel="noopener"&gt;заявил&lt;/a&gt;, что на доплаты для медиков «на следующий год предусмотрен необходимый резерв в резервном фонде, в расходах». Решение о продлении доплат на 2021 год уже принято, заявил «Коммерсанту» источник в социальном блоке правительства.&lt;/p&gt;&lt;p&gt;Подход к администрированию выплат изменится. Если раньше деньги поступали из федерального бюджета в регионы, то теперь будут проходить через один из внебюджетных фондов под руководством Минздрава и Минтруда. Это позволит избежать проблем с определением размера доплат «из-за рассогласованных действий центра и регионов», сказал источник «Коммерсанта» &lt;/p&gt;</content>
</root>