<?xml version="1.0" encoding="UTF-8" standalone="yes"?>
<root>
  <title>СК объявил о возбуждении дела о мошенничестве в отношении «спонсора ФБК»</title>
  <second_title/>
  <description>Следственный комитет РФ заявил, что в отношении «спонсора» Фонда борьбы с коррупцией (ФБК) Александра Хоменко возбуждено дело о мошенничестве.</description>
  <keywords>новости, политика, расследование, репортаж, интервью, реакция, исследование, опрос, тест, президент, приговор, доллар, нефть, экономика, цены, средства, информация, компания, фото, видео, украина, сепаратисты, война, краткий пересказ, бестселлер</keywords>
  <nameTag>новости</nameTag>
  <name>Следственный комитет России</name>
  <url>https://sledcom.ru/news/item/1535287/</url>
  <date>30.1.2021</date>
  <content>&lt;p&gt;Следственный комитет РФ заявил, что в отношении «спонсора» Фонда борьбы с коррупцией (&lt;span data-id="974384" data-title="Фонд борьбы с коррупцией" class="FootnoteLink" data-body="&amp;amp;lt;p&amp;amp;gt;ФБК признан в России «иностранным агентом» (как и многие другие организации и люди). Мы указываем это по требованию властей. Кстати, законы об «иностранных агентах» могут угрожать и &amp;amp;lt;a href=&amp;amp;quot;https://meduza.io/feature/2020/12/28/budte-gotovy-podatsya-v-inoagenty-inache-shtraf-i-vozmozhno-pyat-let-tyurmy&amp;amp;quot; target=&amp;amp;quot;_blank&amp;amp;quot;&amp;amp;gt;лично вам&amp;amp;lt;/a&amp;amp;gt;.&amp;amp;lt;/p&amp;amp;gt;"&gt;ФБК&lt;/span&gt;) Александра Хоменко возбуждено дело о мошенничестве.&lt;/p&gt;&lt;p&gt;Дело, говорится в опубликованном СК сообщении, связано с госконтрактами на капитальный ремонт Сергиево-Посадского социально-экономического техникума, которые в 2017-2019 годах заключили ООО «Строй инжиниринг» и ООО «ВИП Сервис» под руководством Хоменко. Сумму ущерба следствие оценивает в 30 миллионов рублей.&lt;/p&gt;&lt;p&gt;«По имеющимся сведениям, Хоменко оказывал финансовую поддержку Фонду борьбы с коррупцией», сообщает СК, не уточняя, как это связано с уголовным делом. Хоменко объявлен в розыск. По данным СК, он находится на территории Украины.&lt;/p&gt;</content>
</root>