<?xml version="1.0" encoding="UTF-8" standalone="yes"?>
<root>
  <title>Курс доллара на Московской бирже поднялся выше 75 рублей</title>
  <second_title/>
  <description>Курс доллара на торгах Московской биржи утром 22 февраля превысил 75 рублей. </description>
  <keywords>новости, политика, расследование, репортаж, интервью, реакция, исследование, опрос, тест, президент, приговор, доллар, нефть, экономика, цены, средства, информация, компания, фото, видео, украина, сепаратисты, война, краткий пересказ, бестселлер</keywords>
  <nameTag>новости</nameTag>
  <name>Московская биржа</name>
  <url>https://www.moex.com/ru/issue/USD000UTSTOM/CETS</url>
  <date>22.2.2021</date>
  <content>&lt;p&gt;Курс доллара на торгах Московской биржи утром 22 февраля превысил 75 рублей. &lt;/p&gt;&lt;p&gt;В первые часы после начала торгов доллар подорожал почти на рубль. В последний раз американская валюта торговалась выше 75 рублей за доллар 5 февраля.&lt;/p&gt;&lt;p&gt;Евро также вырос к рублю, превысив отметку в 90 рублей за один евро. Это произошло впервые за 10 дней. &lt;/p&gt;</content>
</root>