<?xml version="1.0" encoding="UTF-8" standalone="yes"?>
<root>
  <title>80-летний доставщик газет подумывал о пенсии из-за проблем со здоровьем. Ему подарили электровелосипед — чтобы он и дальше мог заниматься любимым делом</title>
  <second_title/>
  <description>80-летний Джордж Бейли — один из старейших разносчиков газет в Великобритании. Свою первую газету он доставил в 11 лет. Повзрослев, Бейли стал работать биржевым маклером. Однако к пенсии он понял, что снова хочет заниматься любимым делом — разносить газеты.</description>
  <keywords>новости, политика, расследование, репортаж, интервью, реакция, исследование, опрос, тест, президент, приговор, доллар, нефть, экономика, цены, средства, информация, компания, фото, видео, украина, сепаратисты, война, краткий пересказ, бестселлер</keywords>
  <nameTag>шапито</nameTag>
  <name>BBC News</name>
  <url>https://www.bbc.co.uk/news/uk-england-kent-56068052</url>
  <date>15.2.2021</date>
  <content>&lt;p&gt;80-летний Джордж Бейли — один из старейших разносчиков газет в Великобритании. Свою первую газету он доставил в 11 лет. Повзрослев, Бейли стал работать биржевым маклером. Однако к пенсии он понял, что снова хочет заниматься любимым делом — разносить газеты.&lt;/p&gt;&lt;p&gt;В последнее время у Бейли возникли проблемы со здоровьем. Длительные прогулки давались ему уже не так легко, как раньше. Тогда-то он и задумался о возможном уходе.&lt;/p&gt;&lt;p&gt;Однако мысли о вынужденной пенсии остались в прошлом — производитель велосипедов Raleigh and Evans Cycles услышал о проблемах британца и подарил ему электровелосипед! Бейли — в полном восторге. По его словам, у него началась «новая жизнь»: «Знать, что теперь я могу продолжать заниматься тем, что люблю, с небольшой помощью современных технологий, — это фантастика».&lt;/p&gt;&lt;p&gt;Бейли рассчитывает, что с новым электровелосипедом сможет доставлять газеты и в 90 лет.&lt;/p&gt;</content>
</root>