<?xml version="1.0" encoding="UTF-8" standalone="yes"?>
<root>
  <title>Telegram поменял эмодзи с флагом Беларуси, теперь он бело-красно-белый. Провластные СМИ назвали это «диверсией» — и ответили картинкой с Гитлером</title>
  <second_title/>
  <description>В телеграме при отправке эмодзи белорусского флага теперь отображается не стандартный красно-зеленый флаг, а бело-красно-белый. Его использует белорусская оппозиция на акциях протеста, которые начались в стране 9 августа после объявления первых результатов президентских выборов.</description>
  <keywords>новости, политика, расследование, репортаж, интервью, реакция, исследование, опрос, тест, президент, приговор, доллар, нефть, экономика, цены, средства, информация, компания, фото, видео, украина, сепаратисты, война, краткий пересказ, бестселлер</keywords>
  <nameTag>шапито</nameTag>
  <name>Meduza</name>
  <url>https://meduza.io/</url>
  <date>25.8.2020</date>
  <content>&lt;p&gt;В телеграме при отправке эмодзи белорусского флага теперь отображается не стандартный красно-зеленый флаг, а &lt;a href="https://meduza.io/feature/2020/08/13/flag-belorusskogo-protesta-belo-krasno-belyy-a-pochemu-otkuda-on-vzyalsya" target="_blank" rel="noopener"&gt;бело-красно-белый&lt;/a&gt;. Его использует белорусская оппозиция на акциях протеста, которые начались в стране 9 августа после объявления первых результатов президентских выборов.&lt;/p&gt;&lt;p&gt;Для отображения бело-красно-белого флага нужно в настройках мессенджера включить опцию «Крупные эмодзи» (Large Emoji в английском варианте).&lt;/p&gt;&lt;p&gt;Однако если в сообщении кроме эмодзи есть еще какой-то текст, флаг так и останется красно-зеленым.&lt;/p&gt;&lt;p&gt;Белорусское радио «Мир» в своем телеграм-канале уже назвало замену эмодзи «диверсией», а также подсказало, как все это можно обойти. К посту прикрепили фотографию с Гитлером и нацистской символикой. Запись перепостило белорусское государственное информагентство «Белта».&lt;/p&gt;</content>
</root>