<?xml version="1.0" encoding="UTF-8" standalone="yes"?>
<root>
  <title>«Спасибо всем тем, кто мог бы нам помешать, но не успел»</title>
  <second_title>Художник из Екатеринбурга Тимофей Радя сжег гигантскую надпись «Future» на пустыре</second_title>
  <description>Екатеринбургский художник Тимофей Радя опубликовал в соцсетях свою новую работу под названием «Future». Она сделана совместно с фестивалем документального кино Beat Film Festival. Радя на фоне заката поджег гигантские буквы с надписью «Future» («Будущее»). Буквы, составлявшие надпись, в процессе разваливались.</description>
  <keywords>новости, политика, расследование, репортаж, интервью, реакция, исследование, опрос, тест, президент, приговор, доллар, нефть, экономика, цены, средства, информация, компания, фото, видео, украина, сепаратисты, война, краткий пересказ, бестселлер</keywords>
  <nameTag>шапито</nameTag>
  <name>Meduza</name>
  <url/>
  <date>28.7.2020</date>
  <content>&lt;p&gt;Екатеринбургский художник Тимофей Радя опубликовал в соцсетях свою новую работу под названием «Future». Она сделана совместно с фестивалем документального кино Beat Film Festival. Радя на фоне заката поджег гигантские буквы с надписью «Future» («Будущее»). Буквы, составлявшие надпись, в процессе разваливались.&lt;/p&gt;&lt;h3&gt;Фотографии&lt;/h3&gt;&lt;h3&gt;Видео&lt;/h3&gt;&lt;p&gt;«Огонь должен жечь», &lt;a href="https://vk.com/xradyax?w=wall2526967_10323" target="_blank" rel="noopener"&gt;говорится&lt;/a&gt; в подписи к посту. Радя поблагодарил всех за помощь с его новой работой — в том числе тех, «кто мог бы &amp;lt;…&amp;gt; помешать, но не успел».&lt;/p&gt;</content>
</root>