<?xml version="1.0" encoding="UTF-8" standalone="yes"?>
<root>
  <title>Юрий Гальцев ничем не хуже Луи Си Кея! И с главной ролью в сериале «Луи» тоже легко бы справился</title>
  <second_title/>
  <description>Есть дипфейки, которые непросто отличить от реальности — вот, например, ролик с Илоном Маском, который поет про Землю в иллюминаторе. А есть такие, что сразу видно: нет, изначально тут было чье-то другое лицо. Но при этом задумка настолько хороша, что тут же прощаешь любые технические недочеты. Так вот, сериал «Луи», вернее «Юра», с Юрием Гальцевым в главной роли вместо американского комика Луи Си Кея — это гениально! И ничего, что дипфейк получился не самый правдоподобный. Зато можно посмотреть, как Дэвид Линч (он в ролике тоже есть) собеседует Юрия Гальцева.</description>
  <keywords>новости, политика, расследование, репортаж, интервью, реакция, исследование, опрос, тест, президент, приговор, доллар, нефть, экономика, цены, средства, информация, компания, фото, видео, украина, сепаратисты, война, краткий пересказ, бестселлер</keywords>
  <nameTag>шапито</nameTag>
  <name>Meduza</name>
  <url/>
  <date>25.6.2020</date>
  <content>&lt;p&gt;Есть дипфейки, которые непросто отличить от реальности — вот, например, &lt;a href="https://meduza.io/shapito/2020/05/31/ilon-mask-poet-pro-zemlyu-v-illyuminatore-posmotrite-samyy-aktualnyy-dipfeyk-posle-zapuska-crew-dragon" target="_blank" rel="noopener"&gt;ролик&lt;/a&gt; с Илоном Маском, который поет про Землю в иллюминаторе. А есть такие, что сразу видно: нет, изначально тут было чье-то другое лицо. Но при этом задумка настолько хороша, что тут же прощаешь любые технические недочеты. Так вот, сериал «Луи», вернее «Юра», с Юрием Гальцевым в главной роли вместо американского комика Луи Си Кея — это гениально! И ничего, что дипфейк получился не самый правдоподобный. Зато можно посмотреть, как Дэвид Линч (он в ролике тоже есть) собеседует Юрия Гальцева.&lt;/p&gt;&lt;h3&gt;Бонус&lt;/h3&gt;&lt;p&gt;А вот так выглядел бы стендап Елены Степаненко, снятый для стримингового сервиса Netflix.&lt;/p&gt;</content>
</root>