<?xml version="1.0" encoding="UTF-8" standalone="yes"?>
<root>
  <title>Волк из «Ну, погоди!» сменил имидж. Он все еще плохой парень, но уже в модных кроссовках и порезанных джинсах</title>
  <second_title/>
  <description>Чебурашку и смешариков в 3D мы уже видели — настало время Волка из «Ну, погоди!». Вот как он будет выглядеть в новом сезоне мультсериала:</description>
  <keywords>новости, политика, расследование, репортаж, интервью, реакция, исследование, опрос, тест, президент, приговор, доллар, нефть, экономика, цены, средства, информация, компания, фото, видео, украина, сепаратисты, война, краткий пересказ, бестселлер</keywords>
  <nameTag>шапито</nameTag>
  <name>Meduza</name>
  <url/>
  <date>4.6.2020</date>
  <content>&lt;p&gt;Чебурашку и смешариков в 3D мы уже видели — настало время Волка из «Ну, погоди!». Вот как он будет выглядеть в новом сезоне мультсериала:&lt;/p&gt;&lt;p&gt;Mash опубликовал наброски с обновленным образом Волка. Эти изображения «Союзмультфильм» разослал актерам, которые пробуются на роль Волка — актер Анатолий Папанов, озвучивавший героя в классических эпизодах мультсериала, умер еще в 1987 году. В 2000-х Волка озвучивал актер Игорь Христенко.&lt;/p&gt;&lt;p&gt;По информации издания, всего авторы перепробовали более 50 вариаций с образом Волка. Герою нарисовали 18 разных причесок и 4 варианта хвоста. В «Союзмультфильме» уточнили, что представленный образ — это не окончательный вариант.&lt;/p&gt;&lt;p&gt;Премьера новых серий «Ну погоди!» запланирована на лето 2020-го. Последний выпуск мультсериала, «Поймай звезду», вышел в 2017 году.&lt;/p&gt;</content>
</root>