<?xml version="1.0" encoding="UTF-8" standalone="yes"?>
<root>
  <title>На футбольном матче в Южной Корее вместо зрителей посадили секс-кукол. Пришлось извиняться</title>
  <second_title/>
  <description>Южнокорейский футбольный клуб «Сеул» обвинили в использовании секс-кукол на стадионе. Живым болельщикам на матчах появляться нельзя из-за коронавируса, вот им и нашли замену. В итоге представителям клуба пришлось извиняться и объяснять, что никакие это не секс-куклы, а самые обычные манекены. И вообще им просто хотелось внести в игру «элемент веселья». Ведь 8 мая чемпионат Южной Кореи возобновил матчи, а футболистам нужна поддержка!</description>
  <keywords>новости, политика, расследование, репортаж, интервью, реакция, исследование, опрос, тест, президент, приговор, доллар, нефть, экономика, цены, средства, информация, компания, фото, видео, украина, сепаратисты, война, краткий пересказ, бестселлер</keywords>
  <nameTag>шапито</nameTag>
  <name>Associated Press</name>
  <url>https://apnews.com/ab87492351eb6ed6fc7012bbe5b9fc74</url>
  <date>18.5.2020</date>
  <content>&lt;p&gt;Южнокорейский футбольный клуб «Сеул» обвинили в использовании секс-кукол на стадионе. Живым болельщикам на матчах появляться нельзя из-за коронавируса, вот им и нашли замену. В итоге представителям клуба пришлось извиняться и объяснять, что никакие это не секс-куклы, а самые обычные манекены. И вообще им просто хотелось внести в игру «элемент веселья». Ведь 8 мая чемпионат Южной Кореи возобновил матчи, а футболистам нужна поддержка!&lt;/p&gt;&lt;p&gt;Как утверждают представители клуба, производитель манекенов Dalkom неоднократно подчеркивал, что для стадиона предоставят именно манекены, а не секс-куклы. Тем не менее, Dalkom действительно производит надувные куклы (по крайней мере, об этом говорится на сайте компании). А вот почему для стадиона отобрали преимущественно женские манекены, в «Сеуле» объяснять не стали.&lt;/p&gt;</content>
</root>