<?xml version="1.0" encoding="UTF-8" standalone="yes"?>
<root>
  <title>В ночные клубы Москвы будут пускать по QR-кодам и СМС</title>
  <second_title/>
  <description>С 19 октября по 1 ноября в Москве из-за распространения коронавируса вводится особый режим доступа в ночные клубы, дискотеки, бары и другие развлекательные заведения. Об этом сообщается на сайте мэра Москвы Сергея Собянина.</description>
  <keywords>новости, политика, расследование, репортаж, интервью, реакция, исследование, опрос, тест, президент, приговор, доллар, нефть, экономика, цены, средства, информация, компания, фото, видео, украина, сепаратисты, война, краткий пересказ, бестселлер</keywords>
  <nameTag>новости</nameTag>
  <name>Сергей Собянин</name>
  <url>https://www.sobyanin.ru/koronavirus-diskoteki-o-resheniyah-15-10-2020</url>
  <date>15.10.2020</date>
  <content>&lt;p&gt;С 19 октября по 1 ноября в Москве из-за распространения коронавируса вводится особый режим доступа в ночные клубы, дискотеки, бары и другие развлекательные заведения. Об этом сообщается на сайте мэра Москвы Сергея Собянина.&lt;/p&gt;&lt;p&gt;Вход в заведения, работающие с ноля часов ночи до шести часов утра, будет возможен при условии регистрации номеров телефонов — посетители должны будут сканировать QR-код или отправить СМС на короткий номер 7377.&lt;/p&gt;&lt;p&gt;На подобный эксперимент власти решились после консультаций с представителями развлекательной индустрии, отметил мэр.&lt;/p&gt;&lt;p&gt;Как &lt;a href="https://tass.ru/obschestvo/9724929" target="_blank" rel="noopener"&gt;пояснил&lt;/a&gt; первый замруководителя аппарата мэра Москвы Алексей Немерюк, за отказ использовать систему QR-кодов на входе развлекательные заведения будут штрафовать на суммы до 500 тысяч рублей. Посетителей клубов за отказ пользоваться системой check in штрафовать не будут, добавил он.&lt;/p&gt;</content>
</root>