<?xml version="1.0" encoding="UTF-8" standalone="yes"?>
<root>
  <title>Путин попросил не забывать о риске заражения коронавирусом — «чтобы не пришлось, как весной, прибегать к масштабной практике ограничений»</title>
  <second_title/>
  <description>Президент России Владимир Путин попросил жителей страны проявить «максимальную ответственность» на фоне нового роста случаев коронавируса. Об этом он заявил во время расширенного заседания президиума Госсовета, которое транслировал канал «Россия 24».</description>
  <keywords>новости, политика, расследование, репортаж, интервью, реакция, исследование, опрос, тест, президент, приговор, доллар, нефть, экономика, цены, средства, информация, компания, фото, видео, украина, сепаратисты, война, краткий пересказ, бестселлер</keywords>
  <nameTag>новости</nameTag>
  <name>Россия 24</name>
  <url>https://youtu.be/aLeLKQ7pa_Q?t=165</url>
  <date>28.9.2020</date>
  <content>&lt;p&gt;Президент России Владимир Путин попросил жителей страны проявить «максимальную ответственность» на фоне нового роста случаев коронавируса. Об этом он заявил во время расширенного заседания президиума Госсовета, которое транслировал канал «Россия 24».&lt;/p&gt;&lt;p&gt;«Сейчас я еще раз хотел обратиться ко всем нашим гражданам. Риски, дорогие друзья, сохраняются. Хочу попросить вас помнить об этом и проявлять максимальную ответственность и за себя, и за тех, кто рядом с вами», — сказал Путин.&lt;/p&gt;&lt;p&gt;Он заявил, что борьба с эпидемией еще не закончена, и попросил россиян соблюдать рекомендации врачей.&lt;/p&gt;&lt;p&gt;«Сегодня мы знаем об этой опасной болезни гораздо больше, чем несколько месяцев тому назад. Знаем, как действовать, как строить профилактическую работу. Но сейчас именно от каждого зависит результат наших общих усилий по борьбе с распространением инфекции. Чтобы не пришлось вновь, как весной, прибегать к весьма чувствительной для экономики и обременительной для людей масштабной практике ограничений», — сказал Путин.&lt;/p&gt;</content>
</root>