<?xml version="1.0" encoding="UTF-8" standalone="yes"?>
<root>
  <title>«Для картины безусловно выигрышнее женский образ». Первый канал начнет кастинг на главную роль в фильме, который собираются снимать в космосе</title>
  <second_title/>
  <description>Главную роль в российском фильме с рабочим названием «Вызов», который собираются снимать в космосе, сыграет женщина, сообщает Первый канал.</description>
  <keywords>новости, политика, расследование, репортаж, интервью, реакция, исследование, опрос, тест, президент, приговор, доллар, нефть, экономика, цены, средства, информация, компания, фото, видео, украина, сепаратисты, война, краткий пересказ, бестселлер</keywords>
  <nameTag>новости</nameTag>
  <name>Первый канал</name>
  <url>https://www.1tv.ru/about/news/glavnuyu-rol-v-filme-kotoryy-snimut-na-mks-sygraet-zhenshina</url>
  <date>3.11.2020</date>
  <content>&lt;p&gt;Главную роль в российском фильме с рабочим названием «Вызов», который собираются снимать в космосе, сыграет женщина, сообщает Первый канал.&lt;/p&gt;&lt;p&gt;«Решение принято продюсерами картины в интересах сюжета, — сказано на сайте телеканала. — Для картины безусловно выигрышнее женский образ».&lt;/p&gt;&lt;p&gt;Кастинг объявят в ближайшее время. На Первом канале уточнили, что сначала у создателей фильма было два варианта сценария, отбор на главную роль планировали проводить как среди женщин, так и среди мужчин.&lt;/p&gt;</content>
</root>